rsrc/__init__.py
rsrc/base.py
rsrc/hints.py
rsrc/models.py
rsrc/plugins.py
rsrc-0.1.3.dist-info/LICENSE
rsrc-0.1.3.dist-info/METADATA
rsrc-0.1.3.dist-info/WHEEL
rsrc-0.1.3.dist-info/top_level.txt
rsrc-0.1.3.dist-info/RECORD
