Metadata-Version: 2.1
Name: rsrc
Version: 0.1.3
Summary: Resources management (files/directories/etc.).
Home-page: https://github.com/lycantropos/rsrc/
Author: Azat Ibrakov
Author-email: azatibrakov@gmail.com
License: UNKNOWN
Download-URL: https://github.com/lycantropos/rsrc/archive/master.zip
Platform: UNKNOWN
Requires-Python: >=3.5.3
Requires-Dist: memoir (>=0.0.3)
Requires-Dist: reprit (>=0.3.0)
